downward/__init__.py
downward/cached_revision.py
downward/experiment.py
downward/outcomes.py
downward/suites.py
downward/parsers/__init__.py
downward/parsers/anytime_search_parser.py
downward/parsers/exitcode_parser.py
downward/parsers/planner_parser.py
downward/parsers/single_search_parser.py
downward/parsers/translator_parser.py
downward/reports/__init__.py
downward/reports/absolute.py
downward/reports/compare.py
downward/reports/scatter.py
downward/reports/scatter_matplotlib.py
downward/reports/scatter_pgfplots.py
downward/reports/taskwise.py
lab/__init__.py
lab/cached_revision.py
lab/environments.py
lab/experiment.py
lab/fetcher.py
lab/parser.py
lab/steps.py
lab/tools.py
lab/calls/__init__.py
lab/calls/call.py
lab/data/local-job.py.template
lab/data/run.py.template
lab/data/slurm-job-header.template
lab/data/slurm-run-job-body.template
lab/data/slurm-step-job-body.template
lab/reports/__init__.py
lab/reports/filter.py
lab/reports/markup.py
lab-8.7.dist-info/METADATA
lab-8.7.dist-info/WHEEL
lab-8.7.dist-info/licenses/LICENSE.txt
lab-8.7.dist-info/RECORD
