Metadata-Version: 2.4
Name: lab
Version: 8.7
Summary: Benchmark your code
Project-URL: Homepage, https://github.com/aibasel/lab
Author-email: Jendrik Seipp <jendrikseipp@gmail.com>
License: GPL3+
License-File: LICENSE.txt
Keywords: benchmarks,cluster,grid
Classifier: Development Status :: 5 - Production/Stable
Classifier: Environment :: Console
Classifier: Intended Audience :: Science/Research
Classifier: License :: OSI Approved :: GNU General Public License v3 or later (GPLv3+)
Classifier: Programming Language :: Python
Classifier: Programming Language :: Python :: 3.10
Classifier: Programming Language :: Python :: 3.11
Classifier: Programming Language :: Python :: 3.12
Classifier: Programming Language :: Python :: 3.13
Classifier: Programming Language :: Python :: 3.14
Classifier: Topic :: Scientific/Engineering
Requires-Python: >=3.10
Requires-Dist: matplotlib
Requires-Dist: simplejson
Requires-Dist: txt2tags>=3.6
